[
  {
    "name": "Ale",
    "age": 25,
    "city": "Bogotá",
    "createDate": "2025-07-20T05:13:49.072Z"
  },
  {
    "name": "Neo",
    "age": 14,
    "city": "Bogotá",
    "createDate": "2025-07-20T05:14:13.168Z"
  },
  {
    "name": "Miguel",
    "age": 23,
    "city": "Mérida",
    "createDate": "2025-07-20T05:14:35.392Z"
  },
  {
    "name": "Vero",
    "age": 12,
    "city": "Caracas",
    "createDate": "2025-07-20T05:14:48.792Z"
  },
  {
    "name": "Sergio",
    "age": 43,
    "city": "Caracas",
    "createDate": "2025-07-20T05:22:19.890Z"
  },
  {
    "name": "Charo",
    "age": 44,
    "city": "Bqto",
    "createDate": "2025-07-20T05:24:52.432Z"
  },
  {
    "name": "sadas",
    "age": 23,
    "city": "sad",
    "createDate": "2025-07-20T05:30:06.270Z"
  },
  {
    "name": "dsada",
    "age": 333,
    "city": "ddsa",
    "createDate": "2025-07-20T05:30:17.605Z"
  },
  {
    "name": "csacsc",
    "age": 33,
    "city": "2dasd",
    "createDate": "2025-07-20T05:36:33.396Z"
  },
  {
    "name": "33",
    "age": 44,
    "city": "dsad",
    "createDate": "2025-07-20T05:39:49.239Z"
  },
  {
    "name": "sadsa",
    "age": 555,
    "city": "sdsad",
    "createDate": "2025-07-20T05:42:56.948Z"
  },
  {
    "name": "dasd",
    "age": 3333,
    "city": "fsdf",
    "createDate": "2025-07-20T05:43:13.949Z"
  },
  {
    "name": "fsfsd",
    "age": 55,
    "city": "fdfd",
    "createDate": "2025-07-20T05:44:38.109Z"
  }
]